my_math/__init__.py
my_math/basic/__init__.py
my_math/basic/addition.py
my_math/basic/subtraction.py
my_math/intermediate/__init__.py
my_math/intermediate/addition_vec.py
my_math/intermediate/subtraction_vec.py
my_math_math-1.0.0.dist-info/METADATA
my_math_math-1.0.0.dist-info/WHEEL
my_math_math-1.0.0.dist-info/top_level.txt
my_math_math-1.0.0.dist-info/RECORD
